lighting_whisper_mlx/__init__.py
lighting_whisper_mlx/audio.py
lighting_whisper_mlx/decoding.py
lighting_whisper_mlx/lightning.py
lighting_whisper_mlx/load_models.py
lighting_whisper_mlx/timing.py
lighting_whisper_mlx/tokenizer.py
lighting_whisper_mlx/torch_whisper.py
lighting_whisper_mlx/transcribe.py
lighting_whisper_mlx/whisper.py
lightning_whisper_mlx/__init__.py
lightning_whisper_mlx/audio.py
lightning_whisper_mlx/decoding.py
lightning_whisper_mlx/lightning.py
lightning_whisper_mlx/load_models.py
lightning_whisper_mlx/timing.py
lightning_whisper_mlx/tokenizer.py
lightning_whisper_mlx/torch_whisper.py
lightning_whisper_mlx/transcribe.py
lightning_whisper_mlx/whisper.py
lightning_whisper_mlx/assets/download_alice.sh
lightning_whisper_mlx/assets/gpt2.tiktoken
lightning_whisper_mlx/assets/ls_test.flac
lightning_whisper_mlx/assets/mel_filters.npz
lightning_whisper_mlx/assets/multilingual.tiktoken
lightning_whisper_mlx-0.0.10.dist-info/METADATA
lightning_whisper_mlx-0.0.10.dist-info/WHEEL
lightning_whisper_mlx-0.0.10.dist-info/top_level.txt
lightning_whisper_mlx-0.0.10.dist-info/RECORD
